setup.py
sqlite3ct/__init__.py
sqlite3ct/_sqlite3.py
sqlite3ct/callbacks.py
sqlite3ct/dbapi2.py
sqlite3ct/exc.py
sqlite3ct/utils.py
sqlite3ct.egg-info/PKG-INFO
sqlite3ct.egg-info/SOURCES.txt
sqlite3ct.egg-info/dependency_links.txt
sqlite3ct.egg-info/top_level.txt